my_exporter/__init__.py
my_exporter/cli.py
my_exporter/exporter.py
my_exporter/ignore_handler.py
my_exporter/logger.py
my_exporter-0.4.3.dist-info/entry_points.txt
my_exporter-0.4.3.dist-info/LICENSE
my_exporter-0.4.3.dist-info/METADATA
my_exporter-0.4.3.dist-info/WHEEL
my_exporter-0.4.3.dist-info/RECORD
