Metadata-Version: 2.1
Name: my-exporter
Version: 0.4.3
Summary: 
Author: Ryota Kobayashi
Author-email: s.woods.m.29@gmail.com
Requires-Python: >=3.11,<4.0
Classifier: Programming Language :: Python :: 3
Classifier: Programming Language :: Python :: 3.11
Classifier: Programming Language :: Python :: 3.12
Classifier: Programming Language :: Python :: 3.13
Requires-Dist: pathspec (>=0.12.1,<0.13.0)
Requires-Dist: pytest (>=8.3.4,<9.0.0)
Requires-Dist: sphinx-rtd-theme (>=3.0.2,<4.0.0)
